{".value": {"value": {"value": {"value": 1.0548460644047828, "unit": "gram / milliliter", "@type": "openff.evaluator.unit.Quantity"}, "error": {"value": 0.00041773243960201465, "unit": "gram / milliliter", "@type": "openff.evaluator.unit.Quantity"}, "@type": "openff.evaluator.unit.Measurement"}, "gradients": [], "@type": "openff.evaluator.utils.observables.Observable"}, ".time_series_statistics": {"n_total_points": 100, "n_uncorrelated_points": 100, "statistical_inefficiency": 1.0, "equilibration_index": 0, "@type": "openff.evaluator.utils.timeseries.TimeSeriesStatistics"}}