{".value": {"value": {"value": {"value": 82571.81308194056, "unit": "kilojoule / mole", "@type": "openff.evaluator.unit.Quantity"}, "error": {"value": 34.073604723393586, "unit": "kilojoule / mole", "@type": "openff.evaluator.unit.Quantity"}, "@type": "openff.evaluator.unit.Measurement"}, "gradients": [], "@type": "openff.evaluator.utils.observables.Observable"}, ".time_series_statistics": {"n_total_points": 100, "n_uncorrelated_points": 84, "statistical_inefficiency": 1.0, "equilibration_index": 16, "@type": "openff.evaluator.utils.timeseries.TimeSeriesStatistics"}}