{".value": {"value": {"value": {"value": -27484.929313868608, "unit": "kilojoule / mole", "@type": "openff.evaluator.unit.Quantity"}, "error": {"value": 35.08826460380337, "unit": "kilojoule / mole", "@type": "openff.evaluator.unit.Quantity"}, "@type": "openff.evaluator.unit.Measurement"}, "gradients": [], "@type": "openff.evaluator.utils.observables.Observable"}, ".time_series_statistics": {"n_total_points": 100, "n_uncorrelated_points": 49, "statistical_inefficiency": 1.0086015880658485, "equilibration_index": 3, "@type": "openff.evaluator.utils.timeseries.TimeSeriesStatistics"}}